X80x86BaohumoshiXilieJiaocheng/README.md
X80x86BaohumoshiXilieJiaocheng/__init__.py
X80x86BaohumoshiXilieJiaocheng/__main__.py
X80x86BaohumoshiXilieJiaocheng/file.epub
X80x86BaohumoshiXilieJiaocheng/index.html
X80x86BaohumoshiXilieJiaocheng/css/__init__.py
X80x86BaohumoshiXilieJiaocheng/css/annotations.css
X80x86BaohumoshiXilieJiaocheng/css/main.css
X80x86BaohumoshiXilieJiaocheng/css/normalize.css
X80x86BaohumoshiXilieJiaocheng/css/popup.css
X80x86BaohumoshiXilieJiaocheng/font/__init__.py
X80x86BaohumoshiXilieJiaocheng/font/fontello.eot
X80x86BaohumoshiXilieJiaocheng/font/fontello.svg
X80x86BaohumoshiXilieJiaocheng/font/fontello.ttf
X80x86BaohumoshiXilieJiaocheng/font/fontello.woff
X80x86BaohumoshiXilieJiaocheng/img/__init__.py
X80x86BaohumoshiXilieJiaocheng/img/annotator-glyph-sprite.png
X80x86BaohumoshiXilieJiaocheng/img/annotator-icon-sprite.png
X80x86BaohumoshiXilieJiaocheng/img/apple-touch-icon.png
X80x86BaohumoshiXilieJiaocheng/img/cancelfullscreen.png
X80x86BaohumoshiXilieJiaocheng/img/close.png
X80x86BaohumoshiXilieJiaocheng/img/fullscreen.png
X80x86BaohumoshiXilieJiaocheng/img/loader.gif
X80x86BaohumoshiXilieJiaocheng/img/menu-icon.png
X80x86BaohumoshiXilieJiaocheng/img/save.png
X80x86BaohumoshiXilieJiaocheng/img/saved.png
X80x86BaohumoshiXilieJiaocheng/img/settings-s.png
X80x86BaohumoshiXilieJiaocheng/img/settings.png
X80x86BaohumoshiXilieJiaocheng/img/star.png
X80x86BaohumoshiXilieJiaocheng/js/__init__.py
X80x86BaohumoshiXilieJiaocheng/js/epub.js
X80x86BaohumoshiXilieJiaocheng/js/epub.min.js
X80x86BaohumoshiXilieJiaocheng/js/epub.min.map
X80x86BaohumoshiXilieJiaocheng/js/hooks.min.js
X80x86BaohumoshiXilieJiaocheng/js/hooks.min.map
X80x86BaohumoshiXilieJiaocheng/js/reader.js
X80x86BaohumoshiXilieJiaocheng/js/reader.js.map
X80x86BaohumoshiXilieJiaocheng/js/reader.min.js
X80x86BaohumoshiXilieJiaocheng/js/reader.min.map
X80x86BaohumoshiXilieJiaocheng/js/hooks/__init__.py
X80x86BaohumoshiXilieJiaocheng/js/hooks/extensions/__init__.py
x80x86_baohumoshi_xilie_jiaocheng-2024.3.2.0.dist-info/METADATA
x80x86_baohumoshi_xilie_jiaocheng-2024.3.2.0.dist-info/WHEEL
x80x86_baohumoshi_xilie_jiaocheng-2024.3.2.0.dist-info/entry_points.txt
x80x86_baohumoshi_xilie_jiaocheng-2024.3.2.0.dist-info/top_level.txt
x80x86_baohumoshi_xilie_jiaocheng-2024.3.2.0.dist-info/RECORD
